README.md
setup.py
source_hunter/__init__.py
source_hunter/__main__.py
source_hunter/constant.py
source_hunter/finder.py
source_hunter/hunter.py
source_hunter/parser.py
source_hunter/query.py
source_hunter/render.py
source_hunter/result.py
source_hunter.egg-info/PKG-INFO
source_hunter.egg-info/SOURCES.txt
source_hunter.egg-info/dependency_links.txt
source_hunter.egg-info/entry_points.txt
source_hunter.egg-info/requires.txt
source_hunter.egg-info/top_level.txt
source_hunter/models/__init__.py
source_hunter/models/deps_tree.py
source_hunter/models/fnode.py
source_hunter/test/__init__.py
source_hunter/test/parser_test.py
source_hunter/utils/__init__.py
source_hunter/utils/log_utils.py
source_hunter/utils/path_utils.py
source_hunter/utils/path_utils_test.py