Metadata-Version: 2.1
Name: source-hunter
Version: 0.40
Summary: Tool for analysis of code dependency and calling relationship
Home-page: https://github.com/pyeprog/source-hunter
Author: Waylong
Author-email: pyeprog@foxmail.com
License: MIT
Keywords: source,dependency,calling,relationship,graph,analysis
Platform: UNKNOWN
Classifier: Development Status :: 3 - Alpha
Classifier: Intended Audience :: Developers
Classifier: Topic :: Software Development :: Build Tools
Classifier: License :: OSI Approved :: MIT License
Classifier: Programming Language :: Python :: 3
Classifier: Programming Language :: Python :: 3.4
Classifier: Programming Language :: Python :: 3.5
Classifier: Programming Language :: Python :: 3.6
Classifier: Programming Language :: Python :: 3.7
